souptools/__init__.py
souptools/__meta__.py
souptools/css_match.py
souptools/css_parser.py
souptools/css_types.py
souptools/pretty.py
souptools/util.py
soupcsstools-3.11.7.dist-info/LICENSE.md
soupcsstools-3.11.7.dist-info/METADATA
soupcsstools-3.11.7.dist-info/WHEEL
soupcsstools-3.11.7.dist-info/top_level.txt
soupcsstools-3.11.7.dist-info/RECORD
